odoo/addons/mrp_lot_production_date/README.rst
odoo/addons/mrp_lot_production_date/__init__.py
odoo/addons/mrp_lot_production_date/__manifest__.py
odoo/addons/mrp_lot_production_date/i18n/fr.po
odoo/addons/mrp_lot_production_date/i18n/it.po
odoo/addons/mrp_lot_production_date/i18n/mrp_lot_production_date.pot
odoo/addons/mrp_lot_production_date/models/__init__.py
odoo/addons/mrp_lot_production_date/models/mrp_production.py
odoo/addons/mrp_lot_production_date/readme/CONTRIBUTORS.rst
odoo/addons/mrp_lot_production_date/readme/CREDITS.rst
odoo/addons/mrp_lot_production_date/readme/DESCRIPTION.rst
odoo/addons/mrp_lot_production_date/readme/USAGE.rst
odoo/addons/mrp_lot_production_date/static/description/icon.png
odoo/addons/mrp_lot_production_date/static/description/index.html
odoo/addons/mrp_lot_production_date/tests/__init__.py
odoo/addons/mrp_lot_production_date/tests/test_production_date.py
odoo14_addon_mrp_lot_production_date-14.0.1.0.1.dev6.dist-info/METADATA
odoo14_addon_mrp_lot_production_date-14.0.1.0.1.dev6.dist-info/WHEEL
odoo14_addon_mrp_lot_production_date-14.0.1.0.1.dev6.dist-info/top_level.txt
odoo14_addon_mrp_lot_production_date-14.0.1.0.1.dev6.dist-info/RECORD
